natpy/__init__.py
natpy/auto_convert_add.py
natpy/constants.py
natpy/convert.py
natpy/custom_units.py
natpy/default_values.py
natpy/em_system.py
natpy/natural_unit_class.py
NatPy-0.1.4.dist-info/LICENSE
NatPy-0.1.4.dist-info/METADATA
NatPy-0.1.4.dist-info/WHEEL
NatPy-0.1.4.dist-info/top_level.txt
NatPy-0.1.4.dist-info/RECORD
