Metadata-Version: 2.1
Name: NatPy
Version: 0.1.4
Summary: Convert the units of particle physics quantities.
Home-page: https://github.com/AndreScaffidi/NatPy
Author: Tomas Howson and Andre Scaffidi
Author-email: tomas.howson@adelaide.edu.au, andre.scaffidi@adelaide.edu.au
Classifier: Programming Language :: Python :: 3
Classifier: License :: OSI Approved :: MIT License
Classifier: Operating System :: OS Independent
Requires-Python: >=3.7
License-File: LICENSE
Requires-Dist: numpy
Requires-Dist: astropy
